remla24_team8_lib_version/__init__.py
remla24_team8_lib_version/__main__.py
remla24_team8_lib_version/versioning.py
remla24_team8_lib_version-1.0.0.dist-info/METADATA
remla24_team8_lib_version-1.0.0.dist-info/WHEEL
remla24_team8_lib_version-1.0.0.dist-info/entry_points.txt
remla24_team8_lib_version-1.0.0.dist-info/RECORD
