Metadata-Version: 2.1
Name: remla24-team8-lib-version
Version: 1.0.0
Summary: A version-aware library that can can be asked for the version of the library
Author: Tip ten Brink
Author-email: T.M.tenBrink@student.tudelft.nl
Requires-Python: >=3.12,<4.0
Classifier: Programming Language :: Python :: 3
Classifier: Programming Language :: Python :: 3.12
Requires-Dist: requests (>=2.32.3,<3.0.0)
